LMG_Automation/__init__.py
LMG_Automation/automation.py
LMG_Automation/login_generator.py
LMG_Automation/post_install_setup.py
LMG_Automation-0.1.0.dist-info/METADATA
LMG_Automation-0.1.0.dist-info/WHEEL
LMG_Automation-0.1.0.dist-info/entry_points.txt
LMG_Automation-0.1.0.dist-info/top_level.txt
LMG_Automation-0.1.0.dist-info/RECORD
