Metadata-Version: 2.2
Name: LMG_Automation
Version: 0.1.0
Summary: A Python package for automating LMG processes
Author-email: Harshal <harshal.sarode@landmarkgroup.com>
License: MIT
Requires-Python: >=3.9
Requires-Dist: setuptools
Requires-Dist: pandas
Requires-Dist: numpy
Requires-Dist: selenium
Requires-Dist: rsa
Requires-Dist: bs4
Requires-Dist: pywin32
